Metadata-Version: 2.1
Name: cherri
Version: 0.2
Summary: Cherri is a tool for classification of RNA-RNA interactions.
Home-page: https://github.com/teresa-m/Cherri
Author: Teresa Mueller
Author-email: muellert@informatik.uni-freiburg.de
License:               GNU GENERAL PUBLIC LICENSE
Platform: UNKNOWN
License-File: LICENSE
